pymtsp/__init__.py
pymtsp/agents.py
pymtsp/env.py
pymtsp/engine/__init__.py
pymtsp/engine/city.py
pymtsp/engine/depot.py
pymtsp/engine/manager.py
pymtsp/engine/salesman.py
pymtsp/engine/status.py
pymtsp/utils/__init__.py
pymtsp/utils/generate_coords.py
pymtsp/utils/observations.py
pymtsp/utils/process_tour_dict.py
pymtsp/utils/rewards.py
pymtsp/utils/visulization.py
pymtsp-0.2.4.dist-info/METADATA
pymtsp-0.2.4.dist-info/WHEEL
pymtsp-0.2.4.dist-info/top_level.txt
pymtsp-0.2.4.dist-info/RECORD
